odoo/addons/sale_stock_release_channel_delivery_date/README.rst
odoo/addons/sale_stock_release_channel_delivery_date/__init__.py
odoo/addons/sale_stock_release_channel_delivery_date/__manifest__.py
odoo/addons/sale_stock_release_channel_delivery_date/i18n/it.po
odoo/addons/sale_stock_release_channel_delivery_date/i18n/sale_stock_release_channel_delivery_date.pot
odoo/addons/sale_stock_release_channel_delivery_date/models/__init__.py
odoo/addons/sale_stock_release_channel_delivery_date/models/resource_calendar.py
odoo/addons/sale_stock_release_channel_delivery_date/models/sale_order.py
odoo/addons/sale_stock_release_channel_delivery_date/models/sale_order_line.py
odoo/addons/sale_stock_release_channel_delivery_date/models/stock_release_channel.py
odoo/addons/sale_stock_release_channel_delivery_date/models/stock_warehouse.py
odoo/addons/sale_stock_release_channel_delivery_date/readme/CONTRIBUTORS.md
odoo/addons/sale_stock_release_channel_delivery_date/readme/DESCRIPTION.md
odoo/addons/sale_stock_release_channel_delivery_date/static/description/icon.png
odoo/addons/sale_stock_release_channel_delivery_date/static/description/index.html
odoo/addons/sale_stock_release_channel_delivery_date/tests/__init__.py
odoo/addons/sale_stock_release_channel_delivery_date/tests/test_delivery_date.py
odoo_addon_sale_stock_release_channel_delivery_date-18.0.1.0.3.2.dist-info/METADATA
odoo_addon_sale_stock_release_channel_delivery_date-18.0.1.0.3.2.dist-info/WHEEL
odoo_addon_sale_stock_release_channel_delivery_date-18.0.1.0.3.2.dist-info/top_level.txt
odoo_addon_sale_stock_release_channel_delivery_date-18.0.1.0.3.2.dist-info/RECORD
