Metadata-Version: 2.1
Name: odoo-addon-sale_stock_release_channel_delivery_date
Version: 18.0.1.0.3.2
Requires-Python: >=3.10
Requires-Dist: odoo-addon-sale_stock_release_channel_delivery==18.0.*
Requires-Dist: odoo==18.0.*
Summary: Compute expected date based on available release channels
Home-page: https://github.com/OCA/stock-logistics-release-channel
License: AGPL-3
Author: BCIM,Camptocamp,Odoo Community Association (OCA)
Author-email: support@odoo-community.org
Classifier: Programming Language :: Python
Classifier: Framework :: Odoo
Classifier: Framework :: Odoo :: 18.0
Classifier: License :: OSI Approved :: GNU Affero General Public License v3
